pyodbc_unittest/__init__.py
pyodbc_unittest/dbresult.py
pyodbc_unittest/dbtest.py
pyodbc_unittest-0.8.7.dist-info/METADATA
pyodbc_unittest-0.8.7.dist-info/WHEEL
pyodbc_unittest-0.8.7.dist-info/top_level.txt
pyodbc_unittest-0.8.7.dist-info/RECORD
