Metadata-Version: 2.1
Name: pyodbc-unittest
Version: 0.8.7
Summary: The library provides SQL calls for the Python unittest framework
Home-page: https://github.com/eyashin/pyodbc-unittest
Author: Evgeny Yashin
Author-email: yashin.evgeny@gmail.com
License: UNKNOWN
Project-URL: Bug Reports, https://github.com/eyashin/pyodbc-unittest/issues
Project-URL: Source, https://github.com/eyashin/pyodbc-unittest/
Platform: UNKNOWN
Classifier: Programming Language :: Python :: 3
Classifier: License :: OSI Approved :: MIT License
Classifier: Operating System :: OS Independent
Classifier: Topic :: Software Development :: Testing
Classifier: Topic :: Software Development :: Libraries
Requires-Python: >=3.6
